PythonShujufenxiYuWajueShizhanDaiZhushiYuanma/README.md
PythonShujufenxiYuWajueShizhanDaiZhushiYuanma/__init__.py
PythonShujufenxiYuWajueShizhanDaiZhushiYuanma/__main__.py
PythonShujufenxiYuWajueShizhanDaiZhushiYuanma/file.epub
PythonShujufenxiYuWajueShizhanDaiZhushiYuanma/index.html
PythonShujufenxiYuWajueShizhanDaiZhushiYuanma/css/__init__.py
PythonShujufenxiYuWajueShizhanDaiZhushiYuanma/css/annotations.css
PythonShujufenxiYuWajueShizhanDaiZhushiYuanma/css/main.css
PythonShujufenxiYuWajueShizhanDaiZhushiYuanma/css/normalize.css
PythonShujufenxiYuWajueShizhanDaiZhushiYuanma/css/popup.css
PythonShujufenxiYuWajueShizhanDaiZhushiYuanma/font/__init__.py
PythonShujufenxiYuWajueShizhanDaiZhushiYuanma/font/fontello.eot
PythonShujufenxiYuWajueShizhanDaiZhushiYuanma/font/fontello.svg
PythonShujufenxiYuWajueShizhanDaiZhushiYuanma/font/fontello.ttf
PythonShujufenxiYuWajueShizhanDaiZhushiYuanma/font/fontello.woff
PythonShujufenxiYuWajueShizhanDaiZhushiYuanma/img/__init__.py
PythonShujufenxiYuWajueShizhanDaiZhushiYuanma/img/annotator-glyph-sprite.png
PythonShujufenxiYuWajueShizhanDaiZhushiYuanma/img/annotator-icon-sprite.png
PythonShujufenxiYuWajueShizhanDaiZhushiYuanma/img/apple-touch-icon.png
PythonShujufenxiYuWajueShizhanDaiZhushiYuanma/img/cancelfullscreen.png
PythonShujufenxiYuWajueShizhanDaiZhushiYuanma/img/close.png
PythonShujufenxiYuWajueShizhanDaiZhushiYuanma/img/fullscreen.png
PythonShujufenxiYuWajueShizhanDaiZhushiYuanma/img/loader.gif
PythonShujufenxiYuWajueShizhanDaiZhushiYuanma/img/menu-icon.png
PythonShujufenxiYuWajueShizhanDaiZhushiYuanma/img/save.png
PythonShujufenxiYuWajueShizhanDaiZhushiYuanma/img/saved.png
PythonShujufenxiYuWajueShizhanDaiZhushiYuanma/img/settings-s.png
PythonShujufenxiYuWajueShizhanDaiZhushiYuanma/img/settings.png
PythonShujufenxiYuWajueShizhanDaiZhushiYuanma/img/star.png
PythonShujufenxiYuWajueShizhanDaiZhushiYuanma/js/__init__.py
PythonShujufenxiYuWajueShizhanDaiZhushiYuanma/js/epub.js
python_shujufenxi_yu_wajue_shizhan_dai_zhushi_yuanma-2024.3.4.0.dist-info/METADATA
python_shujufenxi_yu_wajue_shizhan_dai_zhushi_yuanma-2024.3.4.0.dist-info/WHEEL
python_shujufenxi_yu_wajue_shizhan_dai_zhushi_yuanma-2024.3.4.0.dist-info/entry_points.txt
python_shujufenxi_yu_wajue_shizhan_dai_zhushi_yuanma-2024.3.4.0.dist-info/top_level.txt
python_shujufenxi_yu_wajue_shizhan_dai_zhushi_yuanma-2024.3.4.0.dist-info/RECORD
